[{"count": 0, "tags": [], "creator": "ehaase@inf.fu-berlin.de", "attachment_id": null, "id": 19021, "time": "2002-07-04T23:09:52Z", "bug_id": 10490, "creation_time": "2002-07-04T23:09:52Z", "is_private": false, "text": "Consider:\n-------\nimport org.apache.bcel.*;\nimport org.apache.bcel.classfile.*;\npublic class Test{\npublic static void main(String[] args){\n JavaClass a = Repository.lookupClass(\"Test\");\n System.out.println(a.instanceOf(Repository.lookupClass(\"java.lang.Object\")));\n}\n}\n-------\nThis fine program tells us \"false\", i.e. \"Test\" is not derived from\n\"java.lang.Object\". *sigh*"}, {"count": 1, "attachment_id": null, "creator": "ehaase@inf.fu-berlin.de", "is_private": false, "id": 19023, "time": "2002-07-04T23:11:42Z", "bug_id": 10490, "creation_time": "2002-07-04T23:11:42Z", "tags": [], "text": "*** Bug 10269 has been marked as a duplicate of this bug. ***"}, {"count": 2, "tags": [], "bug_id": 10490, "attachment_id": null, "id": 19053, "creation_time": "2002-07-05T11:58:14Z", "time": "2002-07-05T11:58:14Z", "creator": "ehaase@inf.fu-berlin.de", "text": "\nThe bug is in the CVS version of 05-Jul-2002, 13:00 CET;\n\nPeter Schneider <schneidp@lathanda.de> reports the Test.java\nprogram prints the correct \"true\" value on BCEL 5.0.\n", "is_private": false}, {"count": 3, "tags": [], "bug_id": 10490, "attachment_id": null, "id": 19063, "creation_time": "2002-07-05T14:19:34Z", "time": "2002-07-05T14:19:34Z", "creator": "ehaase@inf.fu-berlin.de", "text": "\nConfirm: 5.0 did not have this bug.", "is_private": false}, {"count": 4, "tags": [], "creator": "schneidp@lathanda.de", "attachment_id": null, "id": 19072, "creation_time": "2002-07-05T17:27:56Z", "time": "2002-07-05T17:27:56Z", "bug_id": 10490, "text": "I located that bug.\nJavaClass#getSuperClass will never return java.lang.Object\ntherefore getSuperClasses() doesn't contain java.lang.Object\nTo fix it change getSuperclassName to getClassName\n\n   public JavaClass getSuperClass() {\n    if(\"java.lang.Object\".equals(getSuperclassName())) {//<--------\n      return null;\n    }\n", "is_private": false}]