[{"count": 0, "tags": [], "text": "The relevant include file on AIX 5.1 reads:\n\n/*\n * Select uses bit masks of file descriptors.\n * These macros manipulate such bit fields.\n * FD_SETSIZE may be defined by the user to the maximum valued file\n * descriptor to be selected; the default here should be == OPEN_MAX\n */\n#ifndef FD_SETSIZE\n#define FD_SETSIZE     32767    /* must be == OPEN_MAX in <limits.h> */\n#endif\n\nIncidentically, this is exactly the same as found under 4.3.3.", "is_private": false, "id": 22932, "creator": "Lars-Owe.Ivarsson@its.uu.se", "time": "2002-09-16T17:17:44Z", "bug_id": 12695, "creation_time": "2002-09-16T17:17:44Z", "attachment_id": null}, {"count": 1, "tags": [], "creator": "slive@apache.org", "text": "Thanks.  This info will be included in the next release.", "id": 26427, "time": "2002-11-17T02:06:52Z", "bug_id": 12695, "creation_time": "2002-11-17T02:06:52Z", "is_private": false, "attachment_id": null}]