[{"count": 0, "tags": [], "creator": "agusmba@terra.es", "attachment_id": null, "id": 23611, "time": "2002-09-28T15:57:10Z", "bug_id": 13113, "creation_time": "2002-09-28T15:57:10Z", "is_private": false, "text": "- Added release 1.8-dev\n- Modified release 1.7-dev to match the english version\n- Added a mostly empty action to release 0.13.0 so the xml file is valid as per\nits dtd. (this is missing from the english version too, but I won't submit that yet)\n\nI made the patch with\ncvs -u -w changes.xml\n\nthe -w to ignore spaces because otherwise the whole file came out in the diff.\nThere must be a problem with EOLs or something like that.\nI'm using jEdit in WinXP to edit the xml files."}, {"count": 1, "tags": [], "bug_id": 13113, "attachment_id": 3280, "text": "Created attachment 3280\nplain text patch for changes.xml (spanish)", "id": 23612, "time": "2002-09-28T15:57:39Z", "creator": "agusmba@terra.es", "creation_time": "2002-09-28T15:57:39Z", "is_private": false}, {"count": 2, "tags": [], "bug_id": 13113, "attachment_id": null, "text": "Added [PATCH] to Summary", "id": 23622, "time": "2002-09-29T13:57:55Z", "creator": "agusmba@terra.es", "creation_time": "2002-09-29T13:57:55Z", "is_private": false}, {"count": 3, "tags": [], "bug_id": 13113, "attachment_id": null, "text": "Es completo.  Please cross check.", "id": 23709, "time": "2002-10-01T19:10:25Z", "creator": "poi-support@buni.org", "creation_time": "2002-10-01T19:10:25Z", "is_private": false}, {"count": 4, "tags": [], "bug_id": 13113, "attachment_id": null, "id": 23710, "creation_time": "2002-10-01T19:10:54Z", "time": "2002-10-01T19:10:54Z", "creator": "poi-support@buni.org", "text": "..", "is_private": false}]