[{"count": 0, "text": "I will attach a patch to the regexFunction documentation to provide details of a\nchange committed recently by Mike.", "bug_id": 15425, "is_private": false, "id": 27916, "time": "2002-12-17T02:14:05Z", "creator": "seade@apache.org", "creation_time": "2002-12-17T02:14:05Z", "tags": [], "attachment_id": null}, {"count": 1, "text": "Created attachment 4192\nAdds detail to regexFunction documentation.", "bug_id": 15425, "is_private": false, "id": 27918, "time": "2002-12-17T02:16:51Z", "creator": "seade@apache.org", "creation_time": "2002-12-17T02:16:51Z", "tags": [], "attachment_id": 4192}, {"count": 2, "tags": [], "bug_id": 15425, "attachment_id": null, "id": 28812, "time": "2003-01-02T01:07:36Z", "creator": "jsalvata@atg.com", "creation_time": "2003-01-02T01:07:36Z", "is_private": false, "text": "Applied Scott's patch. Marking as RESOLVED."}, {"count": 3, "attachment_id": null, "bug_id": 15425, "text": "Bulk-editing to close all bugs reported fixed by 1.8.1.", "id": 32822, "time": "2003-03-10T09:40:37Z", "creator": "jsalvata@atg.com", "creation_time": "2003-03-10T09:40:37Z", "tags": [], "is_private": false}]