[{"count": 0, "tags": [], "creator": "tom@dbservice.com", "attachment_id": null, "id": 31344, "time": "2003-02-15T21:05:27Z", "bug_id": 17103, "creation_time": "2003-02-15T21:05:27Z", "is_private": false, "text": "i'm missing something a makefile has: the ability to 'fill' a proprety with a\noutput of a command, something like this:\n\nCFLAGS = `pkg-config --cflags gtk+-2.0`\nthis fills the variable CFLAGS with the output of the command \"pkg-config\n--cflags gtk+-2.0\", very usefull if you develop applications with glib, gtk,\ngnome...\n\ni tried to make my own property (IProperty), but with no success\ni can send you that what i've made so far\n\ntom"}, {"count": 1, "tags": [], "creator": "conor@apache.org", "attachment_id": null, "id": 31361, "time": "2003-02-16T14:32:47Z", "bug_id": 17103, "creation_time": "2003-02-16T14:32:47Z", "is_private": false, "text": "Look at the outputproperty attribute of <exec>"}]