[{"count": 0, "tags": [], "creator": "aolserver@aol.net", "text": "Please find archive with sources for nsjk2 module at the URL above. The module\ntargets AOLserver 4.0 beta 3 or later. The archive structure is rooted at\njakarta-tomcat-connectors-4.1.18-src, and one can extract files directly into\nthe JTC-4.1.18 sources. 4.1.18 is not specifically targeted, any later version\nof jakarta-tomcat-connectors should do. \n\nI have successfully built nsjk2 on Solaris 2.7, with gcc 2.95.2 or Forte Tools 6.", "id": 33706, "time": "2003-03-24T17:26:37Z", "bug_id": 18283, "creation_time": "2003-03-24T17:26:37Z", "is_private": false, "attachment_id": null}, {"attachment_id": 5479, "tags": [], "creator": "aolserver@aol.net", "text": "Created attachment 5479\nSources for nsjk2 module", "count": 1, "id": 33707, "time": "2003-03-24T17:33:20Z", "bug_id": 18283, "creation_time": "2003-03-24T17:33:20Z", "is_private": false}]