[{"count": 0, "tags": [], "bug_id": 18518, "text": "modules/aaa/config.m4 has hardcoded include path for APR. This doesn't work when\nAPR is installed in system and included one from tarball is not used.\nThis patch fix it.\n\n--- apache2-2.0.44/modules/aaa/config.m4~       2003-03-25 12:32:35 +0300\n+++ apache2-2.0.44/modules/aaa/config.m4        2003-03-25 12:32:18 +0300\n@@ -11,7 +11,7 @@\n \n APACHE_MODULE(auth_digest, RFC2617 Digest authentication, , , most, [\n   ap_old_cppflags=$CPPFLAGS\n-  CPPFLAGS=\"$CPPFLAGS -I$APR_SOURCE_DIR/include -I$abs_builddir/srclib/apr/include\"\n+  CPPFLAGS=\"$CPPFLAGS $INCLUDES\"\n   AC_TRY_COMPILE([#include <apr.h>], \n                  [#if !APR_HAS_RANDOM \n                   #error You need APR random support to use auth_digest.", "id": 34175, "time": "2003-03-31T13:39:00Z", "creator": "svd@altlinux.ru", "creation_time": "2003-03-31T13:39:00Z", "is_private": false, "attachment_id": null}, {"count": 1, "tags": [], "bug_id": 18518, "text": "This should be fixed in 2.0.45 - can you try that version instead?", "id": 34450, "time": "2003-04-03T15:57:04Z", "creator": "jorton@redhat.com", "creation_time": "2003-04-03T15:57:04Z", "is_private": false, "attachment_id": null}, {"count": 2, "tags": [], "creator": "svd@altlinux.ru", "text": "Version 2.0.45 works correctly", "id": 34493, "time": "2003-04-04T07:48:25Z", "bug_id": 18518, "creation_time": "2003-04-04T07:48:25Z", "is_private": false, "attachment_id": null}]