[{"count": 0, "text": "During the execution of an stcheckout task, I supplied a 4.0 version of the \nstarteam-sdk.jar and received an exception because the BuildNumber class did \nnot contain a getDisplayString() method.  This method was added in a later \nversion of the starteam sdk.  I have obtained a later version of the starteam-\nsdk.jar, but a fix may need to be added for backward compatibility.", "creator": "bob_kimball@yahoo.com", "attachment_id": null, "id": 35116, "time": "2003-04-14T15:15:02Z", "bug_id": 18997, "creation_time": "2003-04-14T15:15:02Z", "tags": [], "is_private": false}, {"count": 1, "tags": [], "bug_id": 18997, "attachment_id": null, "id": 165943, "time": "2013-03-18T02:25:48Z", "creator": "antoine@apache.org", "creation_time": "2013-03-18T02:25:48Z", "is_private": false, "text": "starteam ant tasks have been removed starting with Ant 1.8.0"}]