[{"attachment_id": null, "tags": [], "creator": "jwjansen@xs4all.nl", "text": "I have defined a local domain (willebil.nl) running on an local dns server. I \nwant to use two virtual hosts at ip addr. 10.0.0.141. Therefore i have created \nan config that looks like the example below. When i restart the server and open \na browser session like http://phpdevelop.willebil.nl then i get the original \ninstallation version, the same if i use phpnuke.\nIn the access_log i find the following entries:\n\n10.0.0.151 - - [10/Aug/2003:13:46:21 +0200] \"GET / HTTP/1.1\" 403 2898 \"-\n\" \"Mozilla/4.0 (compatible; MSIE 6.0; Windows NT 5.0; .NET CLR 1.1.4322)\"\n10.0.0.151 - - [10/Aug/2003:13:46:21 +0200] \"GET /icons/apache_pb.gif HTTP/1.1\" \n304 0 \"http://phpdevelop.willebil.nl/\" \"Mozilla/4.0 (compatible; MSIE 6.0; \nWindows NT 5.0; .NET CLR 1.1.4322)\"\n10.0.0.151 - - [10/Aug/2003:13:46:21 +0200] \"GET /icons/powered_by.gif \nHTTP/1.1\" 304 0 \"http://phpdevelop.willebil.nl/\" \"Mozilla/4.0 (compatible; MSIE \n6.0; Windows NT 5.0; .NET CLR 1.1.4322)\"\n\nWhat am i doing wrong?\n\nthx in advance\n\n------------------------------\nListen 80\nNameVirtualHost *\n<VirtualHost *>\nDocumentRoot /var/www/html\nServerName ncc1701.willebil.nl\n</VirtualHost>\n<VirtualHost *>\nDocumentRoot /var/www/phpdevelop\nServerName phpdevelop.willebil.nl\n</VirtualHost>\n<VirtualHost *>\nDocumentRoot \"/var/www/phpnuke\"\nServerName phpnuke.willebil.nl\n</VirtualHost>", "count": 0, "id": 42498, "time": "2003-08-10T12:04:17Z", "bug_id": 22281, "creation_time": "2003-08-10T12:04:17Z", "is_private": false}, {"count": 1, "attachment_id": null, "creator": "slive@apache.org", "text": "This is a support question, not a bug report.  Please take such\nquestions to a support forum like the users@httpd.apache.org mailing\nlist.  Thanks.\n\n[Hint: your log reports a 403 error, so you have some sort of permissions\nproblem.]", "id": 42692, "time": "2003-08-13T17:17:43Z", "bug_id": 22281, "creation_time": "2003-08-13T17:17:43Z", "tags": [], "is_private": false}]