[{"count": 0, "tags": [], "bug_id": 23177, "attachment_id": null, "text": "Overview Description:\nThe javadoc index of the methods provided by the batik toolkit is one big file,\nround about 5.8 MB (both online and offline versions of docs).\n\nSteps to reproduce:\nGo to the url and click on \"Index\" in the main frame.\n\nActual Results:\nIt takes a long time for loading and slows down the system.\n\nExpected Results:\nThere should be one file for each initial letter, as seen in the original sun\ndocumentation (http://java.sun.com/j2se/1.4.2/docs/api/index.html).\n\nHints:\nUse javadoc -splitindex to generate seperate files.\n\nOccurs on:\nW2K SP3, PIII 1 GHz, 245 MB RAM, Mozilla 1.4\n\nRegards,\nMichael.", "id": 44206, "time": "2003-09-15T14:42:26Z", "creator": "mholti@web.de", "creation_time": "2003-09-15T14:42:26Z", "is_private": false}, {"count": 1, "tags": [], "bug_id": 23177, "attachment_id": null, "id": 45185, "time": "2003-10-07T00:38:30Z", "creator": "deweese@apache.org", "creation_time": "2003-10-07T00:38:30Z", "is_private": false, "text": "The next time we generate javadocs they will use the \none letter index."}]