[{"count": 0, "tags": [], "bug_id": 2821, "attachment_id": null, "is_private": false, "id": 4035, "time": "2001-07-26T04:37:51Z", "creator": "tkormann@apache.org", "creation_time": "2001-07-26T04:37:51Z", "text": "An attempt to display a grayscale JPG in SVGBrowser 1.0 release produces this:\n============================================\njava.awt.image.ImagingOpException: Unable to transform src image\n    at java.awt.image.AffineTransformOp.filter(AffineTransformOp.java:258)\n    at\norg.apache.batik.ext.awt.image.rendered.AffineRed.genRect(AffineRed.java:186)\n    at\norg.apache.batik.ext.awt.image.rendered.AffineRed.copyData(AffineRed.java:106)\n    at\norg.apache.batik.ext.awt.image.rendered.AbstractRed.getData(AbstractRed.java:518)\n    at\norg.apache.batik.ext.awt.image.rendered.Any2sRGBRed.copyData(Any2sRGBRed.java:201)\n    at\norg.apache.batik.ext.awt.image.GraphicsUtil.drawImage(GraphicsUtil.java:344)\n    at\norg.apache.batik.ext.awt.image.GraphicsUtil.drawImage(GraphicsUtil.java:439)\n    at\norg.apache.batik.ext.awt.image.GraphicsUtil.drawImage(GraphicsUtil.java:400)\n    at\norg.apache.batik.gvt.RasterImageNode.primitivePaint(RasterImageNode.java:137)\n    at\norg.apache.batik.gvt.AbstractGraphicsNode.paint(AbstractGraphicsNode.java:398)\n    at\norg.apache.batik.gvt.CompositeGraphicsNode.primitivePaint(CompositeGraphicsNode.java:129)       \nat\norg.apache.batik.gvt.AbstractGraphicsNode.paint(AbstractGraphicsNode.java:398)\n    at org.apache.batik.gvt.ImageNode.paint(ImageNode.java:38)\n    at\norg.apache.batik.gvt.CompositeGraphicsNode.primitivePaint(CompositeGraphicsNode.java:129)       \nat\norg.apache.batik.gvt.CanvasGraphicsNode.primitivePaint(CanvasGraphicsNode.java:61)\n    at\norg.apache.batik.gvt.AbstractGraphicsNode.paint(AbstractGraphicsNode.java:398)\n    at\norg.apache.batik.gvt.CompositeGraphicsNode.primitivePaint(CompositeGraphicsNode.java:129)       \nat\norg.apache.batik.gvt.filter.GraphicsNodeRed8Bit.genRect(GraphicsNodeRed8Bit.java:134)\n    at\norg.apache.batik.ext.awt.image.rendered.AbstractTiledRed.copyToRasterByBlocks(AbstractTiledRed.java:630)\n    at\norg.apache.batik.ext.awt.image.rendered.AbstractTiledRed.copyData(AbstractTiledRed.java:252)\n    at\norg.apache.batik.ext.awt.image.rendered.TranslateRed.copyData(TranslateRed.java:97)\n    at org.apache.batik.ext.awt.image.rendered.PadRed.copyData(PadRed.java:87)\n    at\norg.apache.batik.gvt.renderer.StaticRenderer.repaint(StaticRenderer.java:374)\n    at\norg.apache.batik.swing.gvt.GVTTreeRenderer.run(GVTTreeRenderer.java:105)                 \n===========================================\n\nSVGBrowser run using Java 1.3 under Linux Mandrake 7.2; grayscale image saved\nwith\nGIMP 1.1.25 under Linux.  Grayscale image displays fine with ImageMagick.\n\nThe sample files are ftp'able at ftp://catcode.com/pub/svgtest.zip"}, {"count": 1, "tags": [], "creator": "deweese@apache.org", "attachment_id": null, "is_private": false, "id": 4059, "time": "2001-07-26T11:36:11Z", "bug_id": 2821, "creation_time": "2001-07-26T11:36:11Z", "text": "Worked around a bug in the JDK Affine operation."}]