[{"count": 0, "tags": [], "bug_id": 28733, "attachment_id": null, "text": "No matter what I try, my CGI scripts (that have worked well with Apache 1.3)\nappear in the browser as text when using Apache 2.0!\nI've read the documentation about the required settings and they look OK to me.\nI've queried your bug database, but found nothing of use for me there.\n(Hopefully I've included my httpd.conf file (for upload)).", "id": 56728, "time": "2004-05-02T20:37:04Z", "creator": "pamajoff@yahoo.com", "creation_time": "2004-05-02T20:37:04Z", "is_private": false}, {"count": 1, "tags": [], "creator": "slive@apache.org", "text": "Please ask on a user support forum such as\nhttp://httpd.apache.org/userslist.html\n\nYour problem is almost certainly a configuration error and not a bug.  And even \nif it is a bug, your problem report does not give sufficient information to \nidentify or fix it.  The user support forum can help you in either case.\n\nThanks.", "id": 56732, "time": "2004-05-02T23:39:44Z", "bug_id": 28733, "creation_time": "2004-05-02T23:39:44Z", "is_private": false, "attachment_id": null}]