[{"count": 0, "tags": [], "bug_id": 29243, "attachment_id": null, "is_private": false, "id": 58193, "time": "2004-05-27T09:59:47Z", "creator": "gblock@ctoforaday.com", "creation_time": "2004-05-27T09:59:47Z", "text": "When this happens (truss output)\n\nopen(\"/usr/local/apache2/logs/xml.whatsonwhen.com-access_log\", O_WRONLY|O_APPEND|O_CREAT, \n0666) Err#79 EOVERFLOW\nwrite(21, \" [ T h u   M a y   2 7  \".., 167)    = 167\nwrite(2, \" U n a b l e   t o   o p\".., 20)      = 20\n\nthe system reports...\n\nUnable to open logs\n\n\nIt doesn't say why; it doesn't say which log, nor does it give you any idea of what's actually taking place.\n\nCan that be modified to tell you both which log failed, and what the status code of the open operation \nprovided by the OS was?"}, {"count": 1, "tags": [], "bug_id": 29243, "attachment_id": null, "id": 58669, "time": "2004-06-03T21:48:42Z", "creator": "jorton@redhat.com", "creation_time": "2004-06-03T21:48:42Z", "is_private": false, "text": "mod_log_config writes the error to the error_log, I can't reproduce a problem\nhere with 2.0.49, it looks like shows up in your truss output too:\n\nwrite(21, \" [ T h u   M a y   2 7  \".., 167)    = 167\n\ne.g. by making an access_log into a directory, I get in error_log:\n\n[Thu Jun 03 22:43:39 2004] [error] (21)Is a directory: could not open transfer\nlog file /etc/httpd/logs/access_log.\nUnable to open logs\n\nI think that's the best the module can do.\n"}, {"count": 2, "tags": [], "bug_id": 29243, "attachment_id": null, "is_private": false, "id": 58735, "time": "2004-06-04T11:31:55Z", "creator": "gblock@ctoforaday.com", "creation_time": "2004-06-04T11:31:55Z", "text": "Hmm.  Strange, tho.  It's an oldish Solaris install here - could it be that the problem is with the error \nitself?  Do you get something other than Err#79 when it overflows?"}]