[{"count": 0, "tags": [], "creator": "Robert_Flaherty@Hyperion.com", "attachment_id": null, "id": 59849, "time": "2004-06-24T18:07:39Z", "bug_id": 29789, "creation_time": "2004-06-24T18:07:39Z", "is_private": false, "text": "Currently only StatusLine.getStatusCode() is used to call \nWebdavResource.setStatusCode().  This results in say \"Precondition Failed \n(412)\" instead of \"Precondition Failed: Overwrite header missing or F and \nstate of destination resource at URI /files/test folder2 is not null\".  Also, \npossibly ResponseEntity and the three implementing classes should be altered \nto also maintain/expose message text.  I assume that this text is only \navailable for a single response entity, whereas the multi status response only \nhas the status code (?)."}]