[{"count": 0, "attachment_id": null, "creator": "dog@gnu.org", "is_private": false, "id": 61814, "time": "2004-08-11T13:14:23Z", "bug_id": 30591, "creation_time": "2004-08-11T13:14:23Z", "tags": [], "text": "The Ant build fails if a UTF-8 locale is set with a malformed I/O exception, due to an illegal UTF-8 \ncharacter at line 113, column 19 of src/main/org/apache/tools/ant/filters/ConcatFilter.java"}, {"count": 1, "tags": [], "bug_id": 30591, "text": "Mmmh that should be resolved by 23919 since 2004-10-24 ...\nDo you have an actual version?\n\nRevision 1.4 \nFri Oct 24 06:31:43 2003 UTC (9 months, 2 weeks ago) by antoine \nReplace non ASCII characters by UNICODE escapes\nPR: 23919\nSubmitted by: Martijn Kruithof (ant at kruithof dot xs4all dot nl)\nhttp://cvs.apache.org/viewcvs.cgi/ant/src/main/org/apache/tools/ant/filters/Conc\natFilter.java?rev=1.4&view=markup\n\nWhich character should we use for an apostroph like in \"don't\" ?", "id": 61818, "time": "2004-08-11T13:24:39Z", "creator": "jan@materne.de", "creation_time": "2004-08-11T13:24:39Z", "is_private": false, "attachment_id": null}, {"count": 2, "tags": [], "creator": "peter.reilly@corvil.com", "attachment_id": null, "is_private": false, "id": 61821, "time": "2004-08-11T13:40:27Z", "bug_id": 30591, "creation_time": "2004-08-11T13:40:27Z", "text": "The fix did not make it into the 1.6 branch!\n"}, {"count": 3, "attachment_id": null, "creator": "jan@materne.de", "text": "... when can we get rid off the two development trees ? ...\n\n", "id": 61822, "time": "2004-08-11T13:41:58Z", "bug_id": 30591, "creation_time": "2004-08-11T13:41:58Z", "tags": [], "is_private": false}, {"count": 4, "tags": [], "creator": "conor@apache.org", "attachment_id": null, "is_private": false, "id": 61892, "time": "2004-08-12T14:57:20Z", "bug_id": 30591, "creation_time": "2004-08-12T14:57:20Z", "text": "In any case, I think perhaps we should specify the encoding in the Ant build\nfiles. Best to be explicit."}, {"count": 5, "tags": [], "bug_id": 30591, "text": "Fixed in cvs", "id": 63369, "time": "2004-09-10T16:55:54Z", "creator": "peterreilly@apache.org", "creation_time": "2004-09-10T16:55:54Z", "is_private": false, "attachment_id": null}]