[{"count": 0, "tags": [], "text": "I have configured apache with mod_deflate .\nWhen the server send a html document encoding with deflate ,\nit dont autorise , the http connection does not persist .\n\nIt is normal ? which rfc ?", "attachment_id": null, "bug_id": 34178, "id": 72849, "time": "2005-03-25T15:52:12Z", "creator": "erwan@mas.nom.fr", "creation_time": "2005-03-25T15:52:12Z", "is_private": false}, {"count": 1, "tags": [], "bug_id": 34178, "attachment_id": null, "id": 72977, "time": "2005-03-29T15:12:31Z", "creator": "jorton@redhat.com", "creation_time": "2005-03-29T15:12:31Z", "is_private": false, "text": "mod_deflate does not affect the use of a persistent connection so I'm not sure\nexactly what you're reporting here.  I'd recommend upgrading to 2.0.53 and\nasking a user support forum for further help:\nhttp://httpd.apache.org/lists.html#http-users"}]