[{"count": 0, "tags": [], "bug_id": 3580, "attachment_id": null, "id": 5458, "time": "2001-09-13T04:18:18Z", "creator": "jeff@socialchange.net.au", "creation_time": "2001-09-13T04:18:18Z", "is_private": false, "text": "Hi,\n\nThe docs state that role \"admin\" is checked for by the manager app. Eg, in\nwebapps/tomcat-docs/manager-howto.xml:\n\n&lt;user name=\"craigmcc\" password=\"secret\" roles=\"standard,admin\"&gt;\n\nThis is also what 3.x uses.\n\nHowever, the manager app actually requires role \"manager\". The web.xml contains:\n\n   <auth-constraint>\n       <!-- NOTE:  This role is not present in the default users file -->\n       <role-name>manager</role-name>\n    </auth-constraint>\n\nSo either the docs need to change, or the manager web.xml needs to change.\nPreferably the latter, given the precendent.\n\n--Jeff"}, {"count": 1, "tags": [], "bug_id": 3580, "attachment_id": null, "id": 5480, "time": "2001-09-13T08:54:32Z", "creator": "craig.mcclanahan@sun.com", "creation_time": "2001-09-13T08:54:32Z", "is_private": false, "text": "Fixed in nightly build 20010914, and in rc2 when published.  Thanks.\n"}]