[{"count": 0, "tags": [], "bug_id": 37784, "attachment_id": null, "is_private": false, "id": 83213, "time": "2005-12-05T01:05:10Z", "creator": "alistair@maclean-nj.com", "creation_time": "2005-12-05T01:05:10Z", "text": "The default is nominally /usr/local/apache2. I have a 2.0.55 install I wished to\npreserve. I set the ./configure --prefix= parameter to /usr/local/apache22. It\ncompiled and installed, but looking at the output it showed several directories\nwere updated on the existing apache2 tree, not the new apache22 tree. \n\nFor example, \n\n/usr/bin/install -c -m 755 .libs/libaprutil-1.lai\n/usr/local/apache22/lib/libaprutil-1.la\n/usr/bin/install -c -m 755 .libs/libaprutil-1.a\n/usr/local/apache22/lib/libaprutil-1.a\nranlib /usr/local/apache22/lib/libaprutil-1.a\nchmod 644 /usr/local/apache22/lib/libaprutil-1.a\n\n[ lots of lines ]\n\nInstalling configuration files\n[PRESERVING EXISTING HTDOCS SUBDIR: /usr/local/apache2/htdocs]\n[PRESERVING EXISTING ERROR SUBDIR: /usr/local/apache2/error]\n[PRESERVING EXISTING ICONS SUBDIR: /usr/local/apache2/icons]\n[PRESERVING EXISTING CGI SUBDIR: /usr/local/apache2/cgi-bin]\n\nOnly 3 new directories were created in /usr/local/apache22 (bin, modules, lib).\nAll other updates were done on /usr/local/apache2 directories (conf, include,\nbuild)."}]