[{"count": 0, "tags": [], "bug_id": 38179, "attachment_id": null, "id": 84336, "time": "2006-01-08T11:47:41Z", "creator": "ricco.ho@softhome.net", "creation_time": "2006-01-08T11:47:41Z", "is_private": false, "text": "I have followed the steps in Xindice Wiki which relocating the document storage\nfrom Tomcat webapps Xindice folder to a specific folder. However, I still got my\ndocuments imported loss after Tomcat restart.\n\nThe document configuration is like\n\ndb/hkliss/data/collection1\ndb/hkliss/data/collection2\ndb/hkliss/data/collection3\n\nAfter Tomcat restarts, only db/hkliss is remained with all child collections\ndisappeared."}, {"count": 1, "tags": [], "creator": "vgritsenko@apache.org", "attachment_id": null, "text": "\n\n*** This bug has been marked as a duplicate of 28783 ***", "id": 84381, "time": "2006-01-09T16:50:10Z", "bug_id": 38179, "creation_time": "2006-01-09T16:50:10Z", "is_private": false}]