[{"count": 0, "tags": [], "bug_id": 41249, "attachment_id": null, "text": "Markers with markerUnits=\"userSpaceOnUse\" seem to be clipped as if\nmarkerUnits were \"strokeWidth\". Display is correct when overflow=\"visible\".", "id": 97391, "time": "2006-12-27T20:29:48Z", "creator": "x00000000@freenet.de", "creation_time": "2006-12-27T20:29:48Z", "is_private": false}, {"count": 1, "tags": [], "bug_id": 41249, "text": "Created attachment 19312\ntestcase", "id": 97392, "time": "2006-12-27T20:30:36Z", "creator": "x00000000@freenet.de", "creation_time": "2006-12-27T20:30:36Z", "is_private": false, "attachment_id": 19312}, {"count": 2, "attachment_id": 19330, "bug_id": 41249, "text": "Created attachment 19330\npatch\n\nDon't know if you like the hack with setting strokeWidth to 1.\nIt's the easiest solution, but may be considered bad coding style.\n\nBTW, is it intentional not to scale the values of the clip property with\nstrokeWidth (later in the file)? The spec is unclear to which coordinate\nsystem they should refer, but I'd rather expect them to be in the system\nof the marker contents.", "id": 97479, "time": "2006-12-30T02:53:42Z", "creator": "x00000000@freenet.de", "creation_time": "2006-12-30T02:53:42Z", "tags": [], "is_private": false}]