[{"count": 0, "tags": [], "bug_id": 41353, "is_private": false, "id": 97955, "creation_time": "2007-01-11T10:40:19Z", "time": "2007-01-11T10:40:19Z", "creator": "mbenson@apache.org", "text": "Mail on user@ reported that ConcurrentModificationExceptions were thrown when\nrunning <ant> tasks in <parallel>.", "attachment_id": null}, {"count": 1, "tags": [], "bug_id": 41353, "is_private": false, "text": "fixed in SVN HEAD.", "id": 97962, "time": "2007-01-11T11:22:49Z", "creator": "mbenson@apache.org", "creation_time": "2007-01-11T11:22:49Z", "attachment_id": null}]