[{"count": 0, "tags": [], "bug_id": 41423, "text": "Hi, it seems like I've found a bug in mod_rewrite's behavior (per-dir).\n\nRuleset in .htaccess:\n\nrewriteengine on\nrewriterule ^(.*)$ $1\nrewriterule ^(.*)$ redir.html?$1 [L]\n\nFrom rewrite_log:\n\nrewrite 'abc/def' -> 'abc/def'\nrewrite 'abc/def/def' -> 'redir.html?abc/def/def'\n\nAs shown above - mod_rewrite has corrupted URL (rewritten by 1st rule) by adding\nunexpected '/def' to it. It happens almost in every case when a request\n('abc/def' in example above) is big enough (contains more than one or two\ndirectories).\n\nI've tested it with Apache 2.2.3 (FreeBSD) and Apache 2.0.59 (Windows XP).\nWhat's the reason of this behavior and are there any workarounds?", "id": 98298, "attachment_id": null, "creator": "nikzze@mail.ru", "creation_time": "2007-01-20T00:43:38Z", "time": "2007-01-20T00:43:38Z", "is_private": false}, {"count": 1, "tags": [], "bug_id": 41423, "text": "\n\n*** This bug has been marked as a duplicate of 38642 ***", "id": 98304, "attachment_id": null, "creator": "bobsiegen@googlemail.com", "creation_time": "2007-01-20T07:29:44Z", "time": "2007-01-20T07:29:44Z", "is_private": false}]