[{"count": 0, "tags": [], "bug_id": 43782, "attachment_id": null, "id": 110166, "time": "2007-11-02T06:52:11Z", "creator": "Barthel.Steckemetz@ifb-group.com", "creation_time": "2007-11-02T06:52:11Z", "is_private": false, "text": "The following two bugfixes \n\nhttp://issues.apache.org/bugzilla/show_bug.cgi?id=32099\nhttp://issues.apache.org/bugzilla/show_bug.cgi?id=33882\n\nproduced the wrong result. At the moment fork is always false.\nReason is:\nthe constructor looks like:\n    public Apt() {\n        super();\n        super.setCompiler(AptExternalCompilerAdapter.class.getName());\n        setFork(true);\n    }\n\nBut the setFork-Method was overwritten with:\n\n    public void setFork(boolean fork) {\n        if (!fork) {\n            log(WARNING_IGNORING_FORK, Project.MSG_WARN);\n        }\n    }\n\nProposed solution is a constructor like:\n\n    public Apt() {\n        super();\n        super.setCompiler(AptExternalCompilerAdapter.class.getName());\n        super.setFork(true);\n    }"}, {"count": 1, "tags": [], "bug_id": 43782, "text": "Marking as a duplicate of 33882 - it would have been\nbetter to place the comment on that bug.\n\n\n*** This bug has been marked as a duplicate of 33882 ***", "id": 110168, "time": "2007-11-02T06:56:49Z", "creator": "peterreilly@apache.org", "creation_time": "2007-11-02T06:56:49Z", "is_private": false, "attachment_id": null}, {"count": 2, "tags": [], "text": "\nOh right!\n\nI already saw thats its fixed in subversion.\n\nThanks Peter.", "is_private": false, "bug_id": 43782, "id": 110171, "time": "2007-11-02T07:00:19Z", "creator": "Barthel.Steckemetz@ifb-group.com", "creation_time": "2007-11-02T07:00:19Z", "attachment_id": null}, {"count": 3, "tags": [], "creator": "peterreilly@apache.org", "attachment_id": null, "text": "I am re-opening - it should be \na duplicate of 32099.\n\nThat bug report says that it is nearly impossible to\nget apt to work if fork is false. In the apt code\nthis is now enforced.\n\nIs there something incorrect with the code?\nYour proposed constructer looks the same as the current constructor.\n\n", "id": 110173, "time": "2007-11-02T07:05:18Z", "bug_id": 43782, "creation_time": "2007-11-02T07:05:18Z", "is_private": false}, {"count": 4, "text": "oh, comment clash!\n\nPeter\n", "creator": "peterreilly@apache.org", "attachment_id": null, "id": 110174, "time": "2007-11-02T07:05:44Z", "bug_id": 43782, "creation_time": "2007-11-02T07:05:44Z", "tags": [], "is_private": false}]