[{"count": 0, "attachment_id": null, "bug_id": 438, "is_private": false, "id": 407, "time": "2001-01-12T13:05:50Z", "creator": "dev@tomcat.apache.org", "creation_time": "2001-01-12T13:05:50Z", "tags": [], "text": "With Apache-1.3.14/Tomcat-4.0-b1 running on a linux box with jdk1.3.\r\nApache configured to use port base virtual hosting.\r\nA Cisco Local Directory used to translate http://www.my.com/\r\nto 10.10.10.100:8000 or http://www.my1.com/ to 10.10.10.100:8001.\r\nWhen you access a jsp or servlet on tomcat, tomcat send a Location \r\nheader to the client with the real Apache port.\r\nExample.\r\nThe client access http://www.my.com/examples/jsp Tomcat returns\r\nhttp://www.my.com:8000/exmaples/jsp."}, {"text": "With the current version of Tomcat, you can configure what server port number is\nreturned with the \"proxyPort\" attribute on the <Connector> element.\n", "tags": [], "bug_id": 438, "is_private": false, "count": 1, "id": 3588, "time": "2001-07-10T16:38:20Z", "creator": "craig.mcclanahan@sun.com", "creation_time": "2001-07-10T16:38:20Z", "attachment_id": null}]