[{"count": 0, "tags": [], "bug_id": 44720, "attachment_id": 21745, "is_private": false, "id": 115166, "time": "2008-03-31T15:33:44Z", "creator": "brent.pacheco@cerner.com", "creation_time": "2008-03-31T15:33:44Z", "text": "Created attachment 21745\nContains a wmf image and the resulting svg image after being processed by the ImageTranscoder\n\nWhen running this WMF file through the WMFTranscoder (version 1.7), the resulting SVG image is not displayed properly.  When viewing it in the Adobe SVG Viewer, the entire image is completely black.  When viewing it in Squiggle or Mozilla, there are random black lines on top of the image.  See the attached zip file for the original WMF and resulting SVG files."}, {"count": 1, "tags": [], "bug_id": 44720, "attachment_id": 21746, "text": "Created attachment 21746\nContains another wmf image and the resulting svg image after being processed by the ImageTranscoder", "id": 115167, "time": "2008-03-31T15:38:06Z", "creator": "brent.pacheco@cerner.com", "creation_time": "2008-03-31T15:38:06Z", "is_private": false}, {"count": 2, "tags": [], "creator": "info@dvholten.de", "attachment_id": null, "text": "dont know if that alone is the problem, but the SVG generator produces very strange values for 'stroke-width'...", "id": 146167, "time": "2011-05-06T16:26:13Z", "bug_id": 44720, "creation_time": "2011-05-06T16:26:13Z", "is_private": false}]