[{"count": 0, "tags": [], "bug_id": 48000, "attachment_id": null, "is_private": false, "id": 131137, "time": "2009-10-15T02:44:46Z", "creator": "sacsha30@gmail.com", "creation_time": "2009-10-15T02:44:46Z", "text": "I am trying to apply fallback to my publication modules' resources like javascript, css etc as:\n\n<link rel=\"stylesheet\" type=\"text/css\" href=\"/modules/examplemodule/css/test.css\"/>\n\nbut it is not able to override the code in $LENYA/src/modules/examplemodule/css/test.css with the code $MYPUB/lenya/modules/examplemodule/css/test.css."}]