[{"count": 0, "tags": [], "text": "The \"constant\" fields in tribes.transport.Constants are defined as non-empty public static final byte arrays, so are not actually immutable.\n\nThe _DATA fields only appear to be used in Arrays.equals method calls, so the array comparison could be moved to the Constants class.\n\nThe _COMMAND fields are a bit more difficult to protect, but there could be a getter that returned a copy of the array.", "is_private": false, "bug_id": 49101, "id": 136066, "time": "2010-04-12T16:01:09Z", "creator": "sebb@apache.org", "creation_time": "2010-04-12T16:01:09Z", "attachment_id": null}, {"attachment_id": null, "tags": [], "creator": "markt@apache.org", "is_private": false, "count": 1, "id": 136156, "time": "2010-04-14T18:12:52Z", "bug_id": 49101, "creation_time": "2010-04-14T18:12:52Z", "text": "Leaning towards WONTFIX."}]