[{"count": 0, "tags": [], "creator": "lpinkowski@future-processing.com", "attachment_id": 30182, "is_private": false, "id": 166550, "time": "2013-04-12T12:27:44Z", "bug_id": 54832, "creation_time": "2013-04-12T12:27:44Z", "text": "Created attachment 30182\nTest plan showing the problem.\n\nRegular Expression extractor:\nField: Regular Expression\n\nWhen regular expression definition contains variable reference (${..}) we must quadruple escape backslash. When it doesn't contain variable reference double escaping is enough.\n\nAttached example should explain it better (WARNING - this test plan contains some elements from Google plugins - http://code.google.com/p/jmeter-plugins/)."}, {"count": 1, "tags": [], "bug_id": 54832, "text": "Created attachment 30183\nTest Plan without jmeter plugin", "id": 166555, "time": "2013-04-12T20:42:12Z", "creator": "p.mouawad@ubik-ingenierie.com", "creation_time": "2013-04-12T20:42:12Z", "is_private": false, "attachment_id": 30183}, {"count": 2, "tags": [], "bug_id": 54832, "attachment_id": null, "text": "it is a feature of function parsing as handled by FunctionParser.compileString(String).\n\nBackslash is used as an escape character for the function meta-characters '$' ',' and '\\'.\n\nAt present, one has to double up any backslash characters if a string contains a function reference.\n\nIt's a non-trivial mattter to fix this, and any fix would break existing code.\n\nSee the coloured note towards the end of the following section:\n\nhttp://jmeter.apache.org/usermanual/functions.html#how\n\n*** This bug has been marked as a duplicate of bug 53534 ***", "id": 166559, "time": "2013-04-12T21:03:24Z", "creator": "p.mouawad@ubik-ingenierie.com", "creation_time": "2013-04-12T21:03:24Z", "is_private": false}]