[{"count": 0, "tags": [], "bug_id": 60334, "text": "Created attachment 34415\nTest plan showing issue\n\nFor expression:\n\n$.[state,city]\n\nWe get exception:\n\n Exception: Could not parse token starting at position 2. Expected ?, ', 0-9, * \n\n\nThis works on \n- http://jsonpath.com/\n\n\nI opened bug:\n\nhttps://github.com/jayway/JsonPath/issues/278\n\nI attach test case.", "id": 194786, "time": "2016-11-02T20:13:55Z", "creator": "p.mouawad@ubik-ingenierie.com", "creation_time": "2016-11-02T20:13:55Z", "is_private": false, "attachment_id": 34415}, {"count": 1, "tags": [], "bug_id": 60334, "text": "Java bug fixed as of Java 8 u112", "id": 194867, "time": "2016-11-08T12:49:02Z", "creator": "p.mouawad@ubik-ingenierie.com", "creation_time": "2016-11-08T12:49:02Z", "is_private": false, "attachment_id": null}, {"count": 2, "tags": [], "bug_id": 60334, "attachment_id": null, "is_private": false, "id": 194869, "time": "2016-11-08T12:49:38Z", "creator": "p.mouawad@ubik-ingenierie.com", "creation_time": "2016-11-08T12:49:38Z", "text": "(In reply to Philippe Mouawad from comment #1)\n> Java bug fixed as of Java 8 u112\n\nBad comment"}, {"count": 3, "tags": [], "text": "It appears correct json path should be:\n$.['state','city']", "attachment_id": null, "bug_id": 60334, "id": 195385, "time": "2016-12-06T22:16:47Z", "creator": "p.mouawad@ubik-ingenierie.com", "creation_time": "2016-12-06T22:16:47Z", "is_private": false}]