[{"count": 0, "tags": [], "creator": "mail@stefanheimann.net", "text": "I have created a patch for the tar task. It is now possible the\nspecify a `prefix' attribute in a tarfileset, like in a zipfileset.\n\nExample:\n\n<tar tarfile=\"test7.tar\">\n  <tarfileset dir=\".\" prefix=\"test7-prefix/\">\n    <include name=\"test7dir\"/>\n  </tarfileset>\n</tar>\n\nUnit-test and Tar.java are attached.", "id": 9955, "time": "2002-01-27T16:35:46Z", "bug_id": 6054, "creation_time": "2002-01-27T16:35:46Z", "is_private": false, "attachment_id": null}, {"count": 1, "tags": [], "creator": "mail@stefanheimann.net", "text": "Created attachment 1078\npatch for the tar task", "id": 9956, "time": "2002-01-27T16:38:10Z", "bug_id": 6054, "creation_time": "2002-01-27T16:38:10Z", "is_private": false, "attachment_id": 1078}, {"count": 2, "attachment_id": null, "bug_id": 6054, "text": "Applied to CVS development tree.  Thanks!  Now, a couple of requests:\n- next time, please supply patches using cvs diff -u format.\n- Would you be able to provide a patch for issue \nhttp://nagoya.apache.org/bugzilla/show_bug.cgi?id=5874 also?  This request is\nsimilar to providing a fullpath attribute to tarfileset similar to zipfileset.\n", "id": 10273, "time": "2002-02-03T22:23:52Z", "creator": "umagesh@apache.org", "creation_time": "2002-02-03T22:23:52Z", "tags": [], "is_private": false}, {"count": 3, "tags": [], "bug_id": 6054, "attachment_id": null, "text": "*** Bug 7399 has been marked as a duplicate of this bug. ***", "id": 12229, "time": "2002-03-24T01:45:36Z", "creator": "holtdl@yahoo.com", "creation_time": "2002-03-24T01:45:36Z", "is_private": false}]