[{"count": 0, "text": "I currently can't build POI using Ant 1.4.1 without the following patch.  Yes, \nI agree that it isn't really a POI issue, but still .....", "bug_id": 6900, "is_private": false, "id": 11495, "time": "2002-03-06T07:58:29Z", "creator": "william.barker@wilshire.com", "creation_time": "2002-03-06T07:58:29Z", "tags": [], "attachment_id": null}, {"count": 1, "tags": [], "bug_id": 6900, "text": "Created attachment 1299\nXML Escapes for ENTITY", "id": 11496, "time": "2002-03-06T08:01:32Z", "creator": "william.barker@wilshire.com", "creation_time": "2002-03-06T08:01:32Z", "is_private": false, "attachment_id": 1299}, {"count": 2, "tags": [], "creator": "glens@apache.org", "attachment_id": null, "text": "Seems to have been applied.", "id": 12561, "time": "2002-03-31T04:20:59Z", "bug_id": 6900, "creation_time": "2002-03-31T04:20:59Z", "is_private": false}]