[{"count": 0, "tags": [], "bug_id": 8053, "attachment_id": null, "text": "If a program using org.apache.xerces.parsers.SAXParser attempts to parse a local\nXML file that uses a local XSD schema and the schema has an error, the parser\nreports the error but leaves the schema file opened and locked, which prevents\nsomeone from editing the file to fix the problem. For example:\n\n<?xml version=\"1.0\" encoding=\"UTF-8\"?>\n<db xmlns:xsi=\"http://www.w3.org/2001/XMLSchema-instance\"\n    xsi:noNamespaceSchemaLocation=\"db.xsd\">\n</db>\n\nIf db.xsd has a syntax error, the parser will report it correctly but leave\ndb.xsd opened and locked (rather than closing it as it should). Not a good thing\nwhen the parser in question is being invoked inside an web server (e.g. TomCat).", "id": 13468, "time": "2002-04-13T20:02:43Z", "creator": "nothimtheotherguy@yahoo.com", "creation_time": "2002-04-13T20:02:43Z", "is_private": false}]