[{"count": 0, "tags": [], "text": "The Link to the IDE integration for JBuilder points to an old page.\nThe project is hosted at sourceforge. The homepage is\nhttp://antrunner.sourceforge.net/", "is_private": false, "bug_id": 9988, "id": 18042, "time": "2002-06-19T10:02:33Z", "creator": "dirk.schnelle@web.de", "creation_time": "2002-06-19T10:02:33Z", "attachment_id": null}, {"count": 1, "tags": [], "text": "Fixed in CVS. Thanks.", "attachment_id": null, "bug_id": 9988, "id": 18437, "time": "2002-06-23T21:49:17Z", "creator": "sbailliez@apache.org", "creation_time": "2002-06-23T21:49:17Z", "is_private": false}]